ftpsocket/__init__.py
ftpsocket/__init__.py.bak
ftpsocket/_details.py
ftpsocket/client.py
ftpsocket/commands.py
ftpsocket/server.py
ftpsocket/utils.py
ftpsocket-0.0.1.dist-info/licenses/LICENSE
ftpsocket-0.0.1.dist-info/WHEEL
ftpsocket-0.0.1.dist-info/METADATA
ftpsocket-0.0.1.dist-info/RECORD
