Metadata-Version: 2.4
Name: ftpsocket
Version: 0.0.1
Summary: Internal packages included, don't change any string at here
Author-email: d9c/AYMEN <aymenmw@proton.me>
License-Expression: MIT
License-File: LICENSE
